{"id":118908,"name":"境界の彼方 -I'LL BE HERE- 未来篇","name_cn":"境界的彼方 -I'LL BE HERE- 未来篇","type":"动画","image":"52/87/118908_DCFDk.jpg","link":"https://bgm.tv/subject/118908","eps":1,"collection":{"on_hold":89,"dropped":47,"wish":628,"collect":5225,"doing":79},"date":"2015-04-25","summary":"2013年にTV放送され、2015年春の剧场アニメ化が発表されている『境界の彼方』。「未来篇」はTVシリーズの1年后、未来たちに起こる出来事を描いた完全新作となる。","rating":{"rank":3983,"total":3047,"count":{"1":11,"2":6,"3":21,"4":85,"5":252,"6":868,"7":1239,"8":428,"9":71,"10":66},"score":6.7},"updated_at":"2023-10-13T22:14:00+08:00"}