{"id":311600,"name":"土下座で頼んでみた","name_cn":"试着用土下座来拜托她们吧","type":"动画","image":"82/5d/311600_p49yd.jpg","link":"https://bgm.tv/subject/311600","eps":12,"collection":{"on_hold":56,"dropped":127,"wish":209,"collect":756,"doing":58},"date":"2020-10-14","summary":"ふなつかずきの大人気同人誌シリーズ「土下座で頼んでみた」がまさかのショートアニメ化！\r\n\r\nついつい女の子の色んなものが見たくなっちゃう主人公・土下座。\r\n彼には女の子を口説き落とす最終手段があった。\r\n―― そう、「土下座」である。\r\n「お願い」を聞いてもらうまでひたすら土下座で押し通す土下座、突然の行動に驚き、恥じらい、困惑するヒロインたち…果たして土下座に不可能はないのか！？\r\n最後に女の子たちはみんな見せてくれるのか！？\r\nさあみんなで、「レッツ！土下座！！」","rating":{"rank":7573,"total":467,"count":{"1":16,"2":22,"3":42,"4":77,"5":157,"6":100,"7":34,"8":11,"9":0,"10":8},"score":4.9},"updated_at":"2023-06-26T00:08:32+08:00"}