{"id":397604,"name":"ATRI -My Dear Moments-","name_cn":"亚托莉 -我挚爱的时光-","type":"动画","image":"66/6d/397604_ItlGX.jpg","link":"https://bgm.tv/subject/397604","eps":0,"collection":{"on_hold":23,"dropped":7,"wish":1835,"collect":24,"doing":43},"date":null,"summary":"原因不明の海面上昇によって、地表の多くが海に沈んだ近未来。\r\n幼い頃の事故によって片足を失った少年・斑鳩夏生は、\r\n都市での暮らしに見切りを付け、海辺の田舎町へと移り住んだ。\r\n\r\n身よりのない彼に遺されたのは、海洋地質学者だった祖母の船と潜水艇、\r\nそして借金。夏生は“失った未来”を取り戻すため、\r\n祖母の遺産が眠るという海底の倉庫を目指して潜る。\r\nそこで見つけたのは、棺のような装置の中で眠る不思議な少女―アトリ。\r\n彼女は、人間と見紛うほどに精巧で感情豊かなロボットだった。\r\n海底からサルベージされたアトリは言う。\r\nマスターが残した最後の命令を\r\n果たしたいんです。それまで、\r\nわたしが夏生さんの足になります！\r\n海に沈みゆく穏やかな町で、少年と\r\nロボットの少女の、忘れられない夏が始まる―。","rating":{"rank":0,"total":21,"count":{"1":3,"2":1,"3":0,"4":0,"5":0,"6":0,"7":4,"8":3,"9":4,"10":6},"score":7.3},"updated_at":"2024-03-23T15:30:04+08:00"}