{"id":71802,"name":"げんしけん 二代目","name_cn":"现视研 二代目","type":"动画","image":"de/2a/71802_k0v3u.jpg","link":"https://bgm.tv/subject/71802","eps":13,"collection":{"on_hold":177,"dropped":101,"wish":917,"collect":2471,"doing":206},"date":"2013-07-06","summary":"椎应大学现代视觉文化研究会、通称「现视研」。\r\n成为新会长的荻上千佳，借鉴着去年的迎新活动经验，在今年也力争拉入更多的新生入部。在迎新会场，把仍然自娱自乐地玩着COSPLAY的前会长・大野加奈子放在一边，荻上现场表演了即兴手绘大幅插画的功夫！而对此有所反应的两位女生，新入校的吉武莉华和矢岛美怜也决定加入现视研。所谓物以类聚，这二位自然也不是省油的灯——两人都是腐女子！而更加奇葩的则是出现在部室、希望入部的栗色头发女生，这位清秀美人的真身其实是标准的伪娘・・・\r\n迎接了超有个性的新生们加入，『现视研二代目』的活动即将开始！","rating":{"rank":990,"total":1735,"count":{"1":4,"2":2,"3":4,"4":11,"5":45,"6":186,"7":585,"8":698,"9":146,"10":54},"score":7.5},"updated_at":"2023-10-13T21:52:34+08:00"}